Metadata-Version: 2.1
Name: dadjokes-cli
Version: 0.1.2
Summary: Dad Jokes on your Terminal
Home-page: UNKNOWN
Author: sangarshanan
Author-email: sangarshanan1998@gmail.com
License: UNKNOWN
Platform: UNKNOWN
Provides-Extra: dev
